pure_chacha20.py
pure_chacha20-0.1.0.dist-info/WHEEL
pure_chacha20-0.1.0.dist-info/METADATA
pure_chacha20-0.1.0.dist-info/RECORD
