Metadata-Version: 2.1
Name: pure-chacha20
Version: 0.1.0
Summary: a pure Python implementation of ChaCha20 and XChaCha20
Home-page: https://github.com/oconnor663/pure_python_salsa_chacha
License: CC0-1.0
Author: Jack O'Connor
Author-email: oconnor663@gmail.com
Requires-Python: >=3.6,<4.0
Classifier: License :: CC0 1.0 Universal (CC0 1.0) Public Domain Dedication
Classifier: Programming Language :: Python :: 3
Classifier: Programming Language :: Python :: 3.6
Classifier: Programming Language :: Python :: 3.7
Classifier: Programming Language :: Python :: 3.8
Classifier: Programming Language :: Python :: 3.9
Project-URL: Repository, https://github.com/oconnor663/pure_python_salsa_chacha
